odoo/addons/mail_send_copy/README.rst
odoo/addons/mail_send_copy/__init__.py
odoo/addons/mail_send_copy/__manifest__.py
odoo/addons/mail_send_copy/i18n/fr.po
odoo/addons/mail_send_copy/i18n/mail_send_copy.pot
odoo/addons/mail_send_copy/models/__init__.py
odoo/addons/mail_send_copy/models/ir_mail_server.py
odoo/addons/mail_send_copy/readme/CONTRIBUTORS.rst
odoo/addons/mail_send_copy/readme/DESCRIPTION.rst
odoo/addons/mail_send_copy/readme/ROADMAP.rst
odoo/addons/mail_send_copy/static/description/icon.png
odoo/addons/mail_send_copy/static/description/index.html
odoo/addons/mail_send_copy/tests/__init__.py
odoo/addons/mail_send_copy/tests/test_mail_send_copy.py
odoo_addon_mail_send_copy-15.0.1.0.1.dist-info/METADATA
odoo_addon_mail_send_copy-15.0.1.0.1.dist-info/WHEEL
odoo_addon_mail_send_copy-15.0.1.0.1.dist-info/top_level.txt
odoo_addon_mail_send_copy-15.0.1.0.1.dist-info/RECORD
